shuggie/__init__.py
shuggie/analysis.py
shuggie/executor.py
shuggie/grammar.py
shuggie/io.py
shuggie/py.typed
shuggie/serializer.py
shuggie/validation.py
shuggie-0.0.2.dist-info/LICENSE
shuggie-0.0.2.dist-info/METADATA
shuggie-0.0.2.dist-info/WHEEL
shuggie-0.0.2.dist-info/top_level.txt
shuggie-0.0.2.dist-info/RECORD
