Metadata-Version: 2.1
Name: shuggie
Version: 0.0.2
Summary: Standard Human Understandable Generative Grammar Interpreter and Executor
Author: Josie Yaconelli
License: MIT License
Project-URL: Homepage, https://github.com/jyaconelli/shuggie
Project-URL: Repository, https://github.com/jyaconelli/shuggie
Project-URL: Issue Tracker, https://github.com/jyaconelli/shuggie/issues
Classifier: Programming Language :: Python :: 3
Classifier: Operating System :: OS Independent
Requires-Python: >=3.9
License-File: LICENSE
Provides-Extra: dev
Requires-Dist: pytest>=7.4; extra == "dev"
Requires-Dist: pytest-cov>=4.1; extra == "dev"
Requires-Dist: pre-commit>=3.4; extra == "dev"
Requires-Dist: black>=23.9; extra == "dev"
Requires-Dist: isort>=5.12; extra == "dev"
